matrixx/__init__.py
matrixx/core.py
matrixx-0.1.3.dist-info/METADATA
matrixx-0.1.3.dist-info/WHEEL
matrixx-0.1.3.dist-info/top_level.txt
matrixx-0.1.3.dist-info/RECORD
