Metadata-Version: 2.4
Name: matrixx
Version: 0.1.3
Summary: Lightweight matrix utility library
Home-page: https://github.com/devk-op/matrix-utils
Author: Kranthi
Author-email: kdevprofile@gmail.com
License: MIT
Classifier: Programming Language :: Python :: 3
Classifier: License :: OSI Approved :: MIT License
Classifier: Operating System :: OS Independent
Requires-Python: >=3.6
Requires-Dist: numpy
Dynamic: author
Dynamic: author-email
Dynamic: classifier
Dynamic: description
Dynamic: description-content-type
Dynamic: home-page
Dynamic: license
Dynamic: requires-dist
Dynamic: requires-python
Dynamic: summary
